Metadata-Version: 1.1
Name: Hebel
Version: 0.02.1
Summary: GPU-Accelerated Deep Learning Library in Python
Home-page: https://github.com/hannes-brt/hebel
Author: Hannes Bretschneider
Author-email: hannes@psi.utoronto.ca
License: GPLv2
Keywords: cuda gpu machine-learning deep-learning neural-networks
Platform: UNKNOWN
Classifier: Development Status :: 3 - Alpha
Classifier: Intended Audience :: Science/Research
Classifier: License :: OSI Approved :: GNU General Public License v2 (GPLv2)
Classifier: Programming Language :: C
Classifier: Programming Language :: Python :: 2.7
Classifier: Topic :: Scientific/Engineering :: Artificial Intelligence
Classifier: Topic :: Scientific/Engineering :: Image Recognition
